[
{"id":1,"Rate":"$100", "Title":"Puppy Program","Description":"Sed ut perspiciatis, unde oms iste natus error sit voluptem accudoloremque.","pet_img":"https://onleash.ancorathemes.com/wp-content/uploads/2017/04/service-10-760x410.jpg"},
{"id":2,"Rate":"$140","Title":"Daily Dog Walking","Description":"Sed ut perspiciatis, unde oms iste natus error sit voluptem accudoloremque.","pet_img":"https://onleash.ancorathemes.com/wp-content/uploads/2017/04/service-8-760x410.jpg"},
{"id":3,"Rate":"$190","Title":"Pet Sitting","Description":"Sed ut perspiciatis, unde oms iste natus error sit voluptem accudoloremque.","pet_img":"https://onleash.ancorathemes.com/wp-content/uploads/2017/04/service-7-760x410.jpg"},
{"id":4,"Rate":"$130","Title":"Overnight Care","Description":"Sed ut perspiciatis, unde oms iste natus error sit voluptem accudoloremque.","pet_img":"https://onleash.ancorathemes.com/wp-content/uploads/2017/04/service-4-760x410.jpg"},
{"id":5,"Rate":"$240","Title":"Specialty Service","Description":"Sed ut perspiciatis, unde oms iste natus error sit voluptem accudoloremque.","pet_img":"https://onleash.ancorathemes.com/wp-content/uploads/2017/04/service-5-760x410.jpg"},
{"id":6,"Rate":"$430","Title":"pet shower","Description":"Sed ut perspiciatis, unde oms iste natus error sit voluptem accudoloremque.","pet_img":"https://onleash.ancorathemes.com/wp-content/uploads/2017/04/image-14-760x410.jpg"},
{"id":7,"Rate":"$300","Title":"Nail Cutting","Description":"Sed ut perspiciatis, unde oms iste natus error sit voluptem accudoloremque.","pet_img":"https://onleash.ancorathemes.com/wp-content/uploads/2017/04/service-6-760x410.jpg"},
{"id":8,"Rate":"$250","Title":"Surgery","Description":"Sed ut perspiciatis, unde oms iste natus error sit voluptem accudoloremque.","pet_img":"https://onleash.ancorathemes.com/wp-content/uploads/2017/04/service-5-760x410.jpg"},
{"id":9,"Rate":"$120","Title":"Nail Cutting","Description":"Sed ut perspiciatis, unde oms iste natus error sit voluptem accudoloremque.","pet_img":"https://onleash.ancorathemes.com/wp-content/uploads/2017/04/service-6-760x410.jpg"}
]
